CHANGELOG.md
LICENSE
README.md
science_book/__init__.py
science_book/__version__.py
science_book/physics/__init__.py
science_book/physics/constants/__init__.py
science_book/physics/constants/_constants.py
science_book/physics/mechanics/__init__.py
science_book/physics/mechanics/_mechanics.py
science_book/units/__init__.py
science_book/units/_conversion_factors.py
science_book/units/_prefixes.py
science_book/units/temperature_conversion.py
science_book-0.1.0a0.dev0.dist-info/LICENSE
science_book-0.1.0a0.dev0.dist-info/WHEEL
science_book-0.1.0a0.dev0.dist-info/METADATA
science_book-0.1.0a0.dev0.dist-info/RECORD
